pmotools/__init__.py
pmotools/cli.py
pmotools/pmo_builder/__init__.py
pmotools/pmo_builder/json_convert_utils.py
pmotools/pmo_builder/merge_to_pmo.py
pmotools/pmo_builder/metatable_to_pmo.py
pmotools/pmo_builder/mhap_table_to_pmo.py
pmotools/pmo_builder/panel_information_to_pmo.py
pmotools/pmo_engine/__init__.py
pmotools/pmo_engine/pmo_checker.py
pmotools/pmo_engine/pmo_processor.py
pmotools/pmo_engine/pmo_reader.py
pmotools/pmo_engine/pmo_writer.py
pmotools/schemas/portable_microhaplotype_object_v0.1.0.schema.json
pmotools/scripts/__init__.py
pmotools/scripts/convertors_to_pmo/__init__.py
pmotools/scripts/convertors_to_pmo/excel_meta_to_json_meta.py
pmotools/scripts/convertors_to_pmo/microhaplotype_table_to_json_file.py
pmotools/scripts/convertors_to_pmo/terra_amp_output_to_json.py
pmotools/scripts/convertors_to_pmo/text_meta_to_json_meta.py
pmotools/scripts/extract_info_from_pmo/__init__.py
pmotools/scripts/extract_info_from_pmo/count_library_samples_per_target.py
pmotools/scripts/extract_info_from_pmo/count_specimen_meta.py
pmotools/scripts/extract_info_from_pmo/count_targets_per_library_sample.py
pmotools/scripts/extract_info_from_pmo/extract_insert_of_panels.py
pmotools/scripts/extract_info_from_pmo/extract_refseq_of_inserts_of_panels.py
pmotools/scripts/extract_info_from_pmo/list_bioinformatics_run_names.py
pmotools/scripts/extract_info_from_pmo/list_library_sample_names_per_specimen_name.py
pmotools/scripts/extract_info_from_pmo/list_specimen_meta_fields.py
pmotools/scripts/extractors_from_pmo/__init__.py
pmotools/scripts/extractors_from_pmo/extract_allele_table.py
pmotools/scripts/extractors_from_pmo/extract_pmo_with_read_filter.py
pmotools/scripts/extractors_from_pmo/extract_pmo_with_select_library_sample_names.py
pmotools/scripts/extractors_from_pmo/extract_pmo_with_select_specimen_names.py
pmotools/scripts/extractors_from_pmo/extract_pmo_with_select_targets.py
pmotools/scripts/extractors_from_pmo/extract_pmo_with_selected_meta.py
pmotools-0.1.0.dist-info/WHEEL
pmotools-0.1.0.dist-info/entry_points.txt
pmotools-0.1.0.dist-info/METADATA
pmotools-0.1.0.dist-info/RECORD
