Metadata-Version: 2.3
Name: pmotools
Version: 0.1.0
Summary: Tools for building and analyzing PMO files
Author: Nicholas Hathaway, Kathryn Murie
Author-email: Nicholas Hathaway <nickjhathaway@gmail.com>, Kathryn Murie <kathryn.murie@ucsf.edu>
License:                     GNU GENERAL PUBLIC LICENSE
Requires-Dist: pandas>=2.2.2
Requires-Dist: biopython>=1.83
Requires-Dist: jsonschema>=4.23.0
Requires-Dist: pre-commit
Requires-Python: >=3.11
